{
    "root": "/media/luckie/vol4/semi_supervised_cls/code",
    "program": "train.py",
    "git": {
        "remote": "git@github.com:luckieucas/semi-supervised-cls.git",
        "commit": "1bd7749894fa6241f931b64c5bea125825985871"
    },
    "email": "luckiepeng@163.com",
    "startedAt": "2020-07-22T15:13:03.952762",
    "host": "luckie",
    "username": "luckie",
    "executable": "/home/luckie/anaconda2/envs/py37/bin/python",
    "os": "Linux-4.15.0-111-generic-x86_64-with-debian-buster-sid",
    "python": "3.7.4",
    "gpu": "GeForce RTX 2080 Ti",
    "gpu_count": 2,
    "cpu_count": 32,
    "args": [
        "--exp",
        "0722_frac01_BNM_w50_vat_batch32",
        "--labeled_rate",
        "0.1",
        "--csv_file_train",
        "../dataset/skin/training.csv",
        "--csv_file_test",
        "../dataset/skin/testing.csv",
        "--csv_file_val",
        "../dataset/skin/validation.csv",
        "--task",
        "skin",
        "--bnm_loss",
        "1",
        "--bnm_loss_weight",
        "5",
        "--ema_consistency",
        "0",
        "--vat_loss",
        "1",
        "--gpu",
        "0,1"
    ],
    "state": "killed",
    "jobType": null,
    "mode": "run",
    "name": "skin_0722_frac01_BNM_w50_vat_batch32_densenet121",
    "project": "skin-semi-supervised",
    "heartbeatAt": "2020-07-22T16:14:52.274920",
    "exitcode": 255
}
